Email.py
VTSendEmail-0.0.2.dist-info/LICENSE
VTSendEmail-0.0.2.dist-info/METADATA
VTSendEmail-0.0.2.dist-info/WHEEL
VTSendEmail-0.0.2.dist-info/entry_points.txt
VTSendEmail-0.0.2.dist-info/top_level.txt
VTSendEmail-0.0.2.dist-info/RECORD
