Metadata-Version: 2.1
Name: VTSendEmail
Version: 0.0.2
Summary: Used to send email
Home-page: UNKNOWN
Author: Vijay Thoart
Author-email: vijaythorat0804@gmail.com
License: MIT License
Platform: UNKNOWN
Classifier: Programming Language :: Python :: 3.8
Classifier: Operating System :: OS Independent
Requires-Python: >=3.7
Requires-Dist: Click (==7.0)
Requires-Dist: setuptools (==45.2.0)
